tenantclient/__init__.py
tenantclient/admin.py
tenantclient/apps.py
tenantclient/constants.py
tenantclient/db_router.py
tenantclient/deletion.py
tenantclient/mixins.py
tenantclient/models.py
tenantclient/onboard_new_tenant.py
tenantclient/query.py
tenantclient/serializers.py
tenantclient/tenant_manager.py
tenantclient/tests.py
tenantclient/urls.py
tenantclient/views.py
tenantclient/migrations/__init__.py
tenantclient/services/__init__.py
tenantclient/services/cache_service.py
tenantclient/utils/__init__.py
tenantclient/utils/log_utils.py
tenantclient/utils/tenant_utils.py
tenantclient/utils/thread_container.py
tenantclient-0.0.2.dist-info/METADATA
tenantclient-0.0.2.dist-info/WHEEL
tenantclient-0.0.2.dist-info/top_level.txt
tenantclient-0.0.2.dist-info/RECORD
